MANIFEST.in
setup.py
djvu/__init__.py
djvu/common.pxi
djvu/const.py
djvu/decode.pxd
djvu/decode.pyx
djvu/dllpath.py
djvu/sexpr.pxd
djvu/sexpr.pyx
doc/COPYING
doc/build-reqs.txt
doc/changelog
doc/credits.txt
doc/todo.txt
doc/api/annotations.rst
doc/api/conf.py
doc/api/documents.rst
doc/api/event-model.rst
doc/api/exceptions.rst
doc/api/expressions.rst
doc/api/files.rst
doc/api/geometry.rst
doc/api/index.rst
doc/api/messages.rst
doc/api/outline.rst
doc/api/pages.rst
doc/api/text-zones.rst
examples/djvu-crop-text
examples/djvu-dump-text
examples/djvu2png
private/apt-install-build-reqs
private/build-and-test
private/mingw32-setup-env
python_djvulibre.egg-info/PKG-INFO
python_djvulibre.egg-info/SOURCES.txt
python_djvulibre.egg-info/dependency_links.txt
python_djvulibre.egg-info/top_level.txt
tests/sexpr-gc.py
tests/test_const.py
tests/test_decode.py
tests/test_sexpr.py
tests/tools.py
tests/images/Makefile
tests/images/test0.djvu
tests/images/test0.tex
tests/images/test1.djvu